README.md
setup.cfg
setup.py
circularcoordinates/__init__.py
circularcoordinates/circular_coordinates.py
circularcoordinates/plotting.py
circularcoordinates/scroll.py
circularcoordinates.egg-info/PKG-INFO
circularcoordinates.egg-info/SOURCES.txt
circularcoordinates.egg-info/dependency_links.txt
circularcoordinates.egg-info/requires.txt
circularcoordinates.egg-info/top_level.txt