Metadata-Version: 2.1
Name: circularcoordinates
Version: 0.1.1
Summary: Package contains tools used to create and plot circular coordinates from persistent cohomology 
Home-page: https://github.com/appliedtopology/circular-coordinates
Author: Mikael Vejdemo Johansson, Bilal AbdulRahman
Author-email: mikael.vejdemojohansson@csi.cuny.edu, bilal.z.work@gmail.com
License: MIT
Keywords: python,cohomology,circular coordinates
Platform: UNKNOWN
Classifier: Programming Language :: Python :: 3
